Workbook

Sheet sales_data
A1: Product_ID | B1: Sale_Date | C1: Sales_Rep | D1: Region | E1: Sales_Amount | F1: Quantity_Sold | G1: Product_Category | H1: Unit_Cost | I1: Unit_Price | J1: Customer_Type | K1: Discount | L1: Payment_Method | M1: Sales_Channel | N1: Region_and_Sales_Rep | O1: Order Flag
A2: 1052 | B2: 44960 | C2: Bob | D2: North | E2: 5053.97 | F2: 18 | G2: Furniture | H2: 152.75 | I2: 267.22 | J2: Returning | K2: 0.09 | L2: Cash | M2: Online | N2: North-Bob | O2: =IF(E2>AVERAGE($E$2:$E$1001),"High","Low") -> High
A3: 1093 | B3: 45037 | C3: Bob | D3: West | E3: 4384.02 | F3: 17 | G3: Furniture | H3: 3816.39 | I3: 4209.44 | J3: Returning | K3: 0.11 | L3: Cash | M3: Retail | N3: West-Bob | O3: =IF(E3>AVERAGE($E$2:$E$1001),"High","Low") -> Low
A4: 1015 | B4: 45190 | C4: David | D4: South | E4: 4631.23 | F4: 30 | G4: Food | H4: 261.56 | I4: 371.4 | J4: Returning | K4: 0.2 | L4: Bank Transfer | M4: Retail | N4: South-David | O4: =IF(E4>AVERAGE($E$2:$E$1001),"High","Low") -> Low
A5: 1072 | B5: 45162 | C5: Bob | D5: South | E5: 2167.94 | F5: 39 | G5: Clothing | H5: 4330.03 | I5: 4467.75 | J5: New | K5: 0.02 | L5: Credit Card | M5: Retail | N5: South-Bob | O5: =IF(E5>AVERAGE($E$2:$E$1001),"High","Low") -> Low
A6: 1061 | B6: 45009 | C6: Charlie | D6: East | E6: 3750.2 | F6: 13 | G6: Electronics | H6: 637.37 | I6: 692.71 | J6: New | K6: 0.08 | L6: Credit Card | M6: Online | N6: East-Charlie | O6: =IF(E6>AVERAGE($E$2:$E$1001),"High","Low") -> Low
A7: 1021 | B7: 44968 | C7: Charlie | D7: West | E7: 3761.15 | F7: 32 | G7: Food | H7: 900.79 | I7: 1106.51 | J7: New | K7: 0.21 | L7: Cash | M7: Online | N7: West-Charlie | O7: =IF(E7>AVERAGE($E$2:$E$1001),"High","Low") -> Low
A8: 1083 | B8: 45027 | C8: Bob | D8: West | E8: 618.31 | F8: 29 | G8: Furniture | H8: 2408.81 | I8: 2624.09 | J8: Returning | K8: 0.14 | L8: Cash | M8: Online | N8: West-Bob | O8: =IF(E8>AVERAGE($E$2:$E$1001),"High","Low") -> Low
A9: 1087 | B9: 44932 | C9: Eve | D9: South | E9: 7698.92 | F9: 46 | G9: Furniture | H9: 3702.51 | I9: 3964.65 | J9: New | K9: 0.12 | L9: Bank Transfer | M9: Online | N9: South-Eve | O9: =IF(E9>AVERAGE($E$2:$E$1001),"High","Low") -> High
A10: 1075 | B10: 45106 | C10: David | D10: South | E10: 4223.39 | F10: 30 | G10: Furniture | H10: 738.06 | I10: 1095.4499999999998 | J10: New | K10: 0.05 | L10: Bank Transfer | M10: Online | N10: South-David | O10: =IF(E10>AVERAGE($E$2:$E$1001),"High","Low") -> Low
A11: 1075 | B11: 45208 | C11: Charlie | D11: West | E11: 8239.58 | F11: 18 | G11: Clothing | H11: 2228.35 | I11: 2682.34 | J11: New | K11: 0.13 | L11: Bank Transfer | M11: Online | N11: West-Charlie | O11: =IF(E11>AVERAGE($E$2:$E$1001),"High","Low") -> High
A12: 1088 | B12: 45246 | C12: Eve | D12: North | E12: 8518.45 | F12: 13 | G12: Furniture | H12: 2440.11 | I12: 2517.6 | J12: New | K12: 0.23 | L12: Bank Transfer | M12: Retail | N12: North-Eve | O12: =IF(E12>AVERAGE($E$2:$E$1001),"High","Low") -> High
A13: 1100 | B13: 45152 | C13: Bob | D13: West | E13: 2198.74 | F13: 43 | G13: Food | H13: 1100.81 | I13: 1137.44 | J13: Returning | K13: 0.08 | L13: Bank Transfer | M13: Online | N13: West-Bob | O13: =IF(E13>AVERAGE($E$2:$E$1001),"High","Low") -> Low
A14: 1024 | B14: 45241 | C14: Eve | D14: West | E14: 6607.8 | F14: 21 | G14: Food | H14: 622.01 | I14: 641.09 | J14: Returning | K14: 0 | L14: Bank Transfer | M14: Retail | N14: West-Eve | O14: =IF(E14>AVERAGE($E$2:$E$1001),"High","Low") -> High
A15: 1003 | B15: 45291 | C15: Alice | D15: South | E15: 4775.59 | F15: 30 | G15: Furniture | H15: 4190.28 | I15: 4270.65 | J15: New | K15: 0.2 | L15: Cash | M15: Online | N15: South-Alice | O15: =IF(E15>AVERAGE($E$2:$E$1001),"High","Low") -> Low
A16: 1022 | B16: 45155 | C16: Charlie | D16: South | E16: 8813.55 | F16: 21 | G16: Food | H16: 2537.2 | I16: 2869.6 | J16: New | K16: 0.29 | L16: Bank Transfer | M16: Retail | N16: South-Charlie | O16: =IF(E16>AVERAGE($E$2:$E$1001),"High","Low") -> High
A17: 1053 | B17: 45215 | C17: Bob | D17: North | E17: 2235.83 | F17: 48 | G17: Furniture | H17: 121.19 | I17: 487.65 | J17: New | K17: 0.18 | L17: Cash | M17: Retail | N17: North-Bob | O17: =IF(E17>AVERAGE($E$2:$E$1001),"High","Low") -> Low
A18: 1002 | B18: 45076 | C18: David | D18: North | E18: 6810.35 | F18: 17 | G18: Furniture | H18: 4024.76 | I18: 4420.150000000001 | J18: Returning | K18: 0.04 | L18: Cash | M18: Online | N18: North-David | O18: =IF(E18>AVERAGE($E$2:$E$1001),"High","Low") -> High
A19: 1088 | B19: 45203 | C19: Bob | D19: East | E19: 6116.75 | F19: 40 | G19: Electronics | H19: 4904.93 | I19: 5034.35 | J19: New | K19: 0.1 | L19: Credit Card | M19: Retail | N19: East-Bob | O19: =IF(E19>AVERAGE($E$2:$E$1001),"High","Low") -> High
A20: 1030 | B20: 45124 | C20: David | D20: West | E20: 3023.48 | F20: 19 | G20: Clothing | H20: 3049.33 | I20: 3209.22 | J20: Returning | K20: 0.26 | L20: Cash | M20: Online | N20: West-David | O20: =IF(E20>AVERAGE($E$2:$E$1001),"High","Low") -> Low
A21: 1038 | B21: 44996 | C21: Bob | D21: South | E21: 1452.35 | F21: 15 | G21: Clothing | H21: 2543.36 | I21: 2790.1000000000004 | J21: Returning | K21: 0.07 | L21: Cash | M21: Online | N21: South-Bob | O21: =IF(E21>AVERAGE($E$2:$E$1001),"High","Low") -> Low
A22: 1002 | B22: 45038 | C22: Eve | D22: North | E22: 6551.23 | F22: 9 | G22: Electronics | H22: 4398.16 | I22: 4439.12 | J22: New | K22: 0.18 | L22: Bank Transfer | M22: Online | N22: North-Eve | O22: =IF(E22>AVERAGE($E$2:$E$1001),"High","Low") -> High
A23: 1064 | B23: 44930 | C23: Eve | D23: East | E23: 7412.11 | F23: 10 | G23: Electronics | H23: 4764.96 | I23: 5074.42 | J23: New | K23: 0.12 | L23: Cash | M23: Online | N23: East-Eve | O23: =IF(E23>AVERAGE($E$2:$E$1001),"High","Low") -> High
A24: 1060 | B24: 45276 | C24: Eve | D24: East | E24: 3224.71 | F24: 44 | G24: Clothing | H24: 3784.96 | I24: 4276.99 | J24: New | K24: 0.06 | L24: Bank Transfer | M24: Retail | N24: East-Eve | O24: =IF(E24>AVERAGE($E$2:$E$1001),"High","Low") -> Low
A25: 1021 | B25: 45257 | C25: Alice | D25: South | E25: 6483.84 | F25: 31 | G25: Furniture | H25: 2254.99 | I25: 2441.79 | J25: Returning | K25: 0.24 | L25: Bank Transfer | M25: Online | N25: South-Alice | O25: =IF(E25>AVERAGE($E$2:$E$1001),"High","Low") -> High
A26: 1033 | B26: 45244 | C26: David | D26: South | E26: 4011.8 | F26: 23 | G26: Furniture | H26: 2981.5 | I26: 3360.4 | J26: Returning | K26: 0.22 | L26: Bank Transfer | M26: Retail | N26: South-David | O26: =IF(E26>AVERAGE($E$2:$E$1001),"High","Low") -> Low
A27: 1076 | B27: 45276 | C27: Eve | D27: East | E27: 7160.75 | F27: 30 | G27: Clothing | H27: 3519.63 | I27: 3774.65 | J27: New | K27: 0.2 | L27: Credit Card | M27: Retail | N27: East-Eve | O27: =IF(E27>AVERAGE($E$2:$E$1001),"High","Low") -> High
A28: 1058 | B28: 45021 | C28: Alice | D28: North | E28: 2072.23 | F28: 33 | G28: Furniture | H28: 1011.65 | I28: 1084.28 | J28: Returning | K28: 0.07 | L28: Bank Transfer | M28: Retail | N28: North-Alice | O28: =IF(E28>AVERAGE($E$2:$E$1001),"High","Low") -> Low
A29: 1022 | B29: 45078 | C29: David | D29: East | E29: 8913.13 | F29: 9 | G29: Electronics | H29: 2263.65 | I29: 2558.9500000000003 | J29: New | K29: 0.03 | L29: Cash | M29: Online | N29: East-David | O29: =IF(E29>AVERAGE($E$2:$E$1001),"High","Low") -> High
A30: 1089 | B30: 45237 | C30: Bob | D30: West | E30: 2945.36 | F30: 47 | G30: Furniture | H30: 4157.62 | I30: 4314.5599999999995 | J30: New | K30: 0.17 | L30: Bank Transfer | M30: Retail | N30: West-Bob | O30: =IF(E30>AVERAGE($E$2:$E$1001),"High","Low") -> Low
A31: 1049 | B31: 45063 | C31: Alice | D31: West | E31: 3741.08 | F31: 1 | G31: Furniture | H31: 3290.89 | I31: 3317.75 | J31: Returning | K31: 0.17 | L31: Bank Transfer | M31: Online | N31: West-Alice | O31: =IF(E31>AVERAGE($E$2:$E$1001),"High","Low") -> Low
A32: 1091 | B32: 45173 | C32: Charlie | D32: South | E32: 675.11 | F32: 44 | G32: Food | H32: 2085.46 | I32: 2406.58 | J32: Returning | K32: 0.06 | L32: Bank Transfer | M32: Retail | N32: South-Charlie | O32: =IF(E32>AVERAGE($E$2:$E$1001),"High","Low") -> Low
A33: 1059 | B33: 45169 | C33: Alice | D33: North | E33: 1203.97 | F33: 35 | G33: Food | H33: 3333.64 | I33: 3764.52 | J33: Returning | K33: 0.02 | L33: Credit Card | M33: Online | N33: North-Alice | O33: =IF(E33>AVERAGE($E$2:$E$1001),"High","Low") -> Low
A34: 1042 | B34: 44957 | C34: Alice | D34: North | E34: 5207.03 | F34: 11 | G34: Food | H34: 635.2 | I34: 814.1400000000001 | J34: Returning | K34: 0.02 | L34: Cash | M34: Online | N34: North-Alice | O34: =IF(E34>AVERAGE($E$2:$E$1001),"High","Low") -> High
A35: 1092 | B35: 44966 | C35: David | D35: West | E35: 2749.17 | F35: 34 | G35: Furniture | H35: 2037.41 | I35: 2238.65 | J35: New | K35: 0.3 | L35: Credit Card | M35: Online | N35: West-David | O35: =IF(E35>AVERAGE($E$2:$E$1001),"High","Low") -> Low
A36: 1060 | B36: 45155 | C36: Bob | D36: East | E36: 8371.25 | F36: 16 | G36: Clothing | H36: 3975.99 | I36: 4422.59 | J36: New | K36: 0.24 | L36: Cash | M36: Online | N36: East-Bob | O36: =IF(E36>AVERAGE($E$2:$E$1001),"High","Low") -> High
A37: 1080 | B37: 44962 | C37: Charlie | D37: South | E37: 245.46 | F37: 9 | G37: Electronics | H37: 1141.52 | I37: 1550.19 | J37: New | K37: 0.28 | L37: Credit Card | M37: Retail | N37: South-Charlie | O37: =IF(E37>AVERAGE($E$2:$E$1001),"High","Low") -> Low
A38: 1015 | B38: 45149 | C38: Eve | D38: East | E38: 3853.03 | F38: 32 | G38: Furniture | H38: 970.51 | I38: 1330.84 | J38: Returning | K38: 0.06 | L38: Cash | M38: Retail | N38: East-Eve | O38: =IF(E38>AVERAGE($E$2:$E$1001),"High","Low") -> Low
A39: 1062 | B39: 44932 | C39: Eve | D39: East | E39: 3439.72 | F39: 15 | G39: Clothing | H39: 4756.55 | I39: 4888.46 | J39: New | K39: 0.29 | L39: Credit Card | M39: Online | N39: East-Eve | O39: =IF(E39>AVERAGE($E$2:$E$1001),"High","Low") -> Low
A40: 1062 | B40: 45248 | C40: Alice | D40: East | E40: 291.34 | F40: 12 | G40: Furniture | H40: 1088.99 | I40: 1545 | J40: Returning | K40: 0.04 | L40: Bank Transfer | M40: Retail | N40: East-Alice | O40: =IF(E40>AVERAGE($E$2:$E$1001),"High","Low") -> Low
A41: 1047 | B41: 45146 | C41: David | D41: North | E41: 1331.25 | F41: 33 | G41: Electronics | H41: 1341.55 | I41: 1427.21 | J41: Returning | K41: 0.15 | L41: Credit Card | M41: Online | N41: North-David | O41: =IF(E41>AVERAGE($E$2:$E$1001),"High","Low") -> Low
A42: 1062 | B42: 45001 | C42: David | D42: West | E42: 4195.06 | F42: 45 | G42: Furniture | H42: 4849.6 | I42: 5166.72 | J42: Returning | K42: 0.25 | L42: Credit Card | M42: Online | N42: West-David | O42: =IF(E42>AVERAGE($E$2:$E$1001),"High","Low") -> Low
A43: 1051 | B43: 44930 | C43: Eve | D43: North | E43: 4979.36 | F43: 14 | G43: Electronics | H43: 3686.81 | I43: 3710.92 | J43: New | K43: 0.1 | L43: Bank Transfer | M43: Retail | N43: North-Eve | O43: =IF(E43>AVERAGE($E$2:$E$1001),"High","Low") -> Low
A44: 1055 | B44: 45261 | C44: Charlie | D44: West | E44: 4102.47 | F44: 8 | G44: Furniture | H44: 3513 | I44: 3838.42 | J44: Returning | K44: 0.13 | L44: Bank Transfer | M44: Online | N44: West-Charlie | O44: =IF(E44>AVERAGE($E$2:$E$1001),"High","Low") -> Low
A45: 1064 | B45: 45060 | C45: Bob | D45: South | E45: 5356.28 | F45: 8 | G45: Electronics | H45: 4271.99 | I45: 4417.79 | J45: Returning | K45: 0.04 | L45: Cash | M45: Online | N45: South-Bob | O45: =IF(E45>AVERAGE($E$2:$E$1001),"High","Low") -> High
A46: 1003 | B46: 45044 | C46: Charlie | D46: South | E46: 5991.8 | F46: 27 | G46: Furniture | H46: 623.32 | I46: 853.6600000000001 | J46: Returning | K46: 0.04 | L46: Cash | M46: Online | N46: South-Charlie | O46: =IF(E46>AVERAGE($E$2:$E$1001),"High","Low") -> High
A47: 1051 | B47: 45020 | C47: Bob | D47: East | E47: 198.25 | F47: 12 | G47: Electronics | H47: 3544.48 | I47: 3723.66 | J47: Returning | K47: 0.19 | L47: Cash | M47: Online | N47: East-Bob | O47: =IF(E47>AVERAGE($E$2:$E$1001),"High","Low") -> Low
A48: 1007 | B48: 44988 | C48: Eve | D48: West | E48: 4694.54 | F48: 1 | G48: Food | H48: 2543.26 | I48: 2637.9100000000003 | J48: Returning | K48: 0.2 | L48: Credit Card | M48: Online | N48: West-Eve | O48: =IF(E48>AVERAGE($E$2:$E$1001),"High","Low") -> Low
A49: 1021 | B49: 45120 | C49: Bob | D49: West | E49: 9638.64 | F49: 43 | G49: Furniture | H49: 4154.3 | I49: 4469.07 | J49: Returning | K49: 0.23 | L49: Cash | M49: Retail | N49: West-Bob | O49: =IF(E49>AVERAGE($E$2:$E$1001),"High","Low") -> High
A50: 1073 | B50: 45261 | C50: David | D50: West | E50: 5238.42 | F50: 40 | G50: Furniture | H50: 2565.3 | I50: 3007.4700000000003 | J50: Returning | K50: 0.17 | L50: Credit Card | M50: Retail | N50: West-David | O50: =IF(E50>AVERAGE($E$2:$E$1001),"High","Low") -> High
A51: 1039 | B51: 45129 | C51: Alice | D51: East | E51: 6807.67 | F51: 42 | G51: Clothing | H51: 3120.19 | I51: 3600.14 | J51: Returning | K51: 0.19 | L51: Credit Card | M51: Retail | N51: East-Alice | O51: =IF(E51>AVERAGE($E$2:$E$1001),"High","Low") -> High
A52: 1018 | B52: 44952 | C52: Alice | D52: East | E52: 3187.45 | F52: 11 | G52: Clothing | H52: 2414.82 | I52: 2519.07 | J52: Returning | K52: 0 | L52: Cash | M52: Online | N52: East-Alice | O52: =IF(E52>AVERAGE($E$2:$E$1001),"High","Low") -> Low
A53: 1004 | B53: 45099 | C53: Eve | D53: South | E53: 7762.51 | F53: 39 | G53: Electronics | H53: 2416.89 | I53: 2778.3999999999996 | J53: Returning | K53: 0.05 | L53: Cash | M53: Online | N53: South-Eve | O53: =IF(E53>AVERAGE($E$2:$E$1001),"High","Low") -> High
A54: 1089 | B54: 45226 | C54: David | D54: North | E54: 7751.92 | F54: 43 | G54: Furniture | H54: 3851.45 | I54: 4186.98 | J54: Returning | K54: 0.3 | L54: Credit Card | M54: Online | N54: North-David | O54: =IF(E54>AVERAGE($E$2:$E$1001),"High","Low") -> High
A55: 1060 | B55: 45059 | C55: Charlie | D55: West | E55: 5260.83 | F55: 31 | G55: Electronics | H55: 3161.4 | I55: 3339.66 | J55: Returning | K55: 0.02 | L55: Bank Transfer | M55: Online | N55: West-Charlie | O55: =IF(E55>AVERAGE($E$2:$E$1001),"High","Low") -> High
A56: 1014 | B56: 45252 | C56: David | D56: West | E56: 9762.54 | F56: 17 | G56: Food | H56: 3184.65 | I56: 3204.01 | J56: New | K56: 0.2 | L56: Bank Transfer | M56: Online | N56: West-David | O56: =IF(E56>AVERAGE($E$2:$E$1001),"High","Low") -> High
A57: 1009 | B57: 45044 | C57: Alice | D57: North | E57: 1342.95 | F57: 33 | G57: Clothing | H57: 2278.9 | I57: 2626.9 | J57: New | K57: 0.05 | L57: Credit Card | M57: Online | N57: North-Alice | O57: =IF(E57>AVERAGE($E$2:$E$1001),"High","Low") -> Low
A58: 1090 | B58: 45250 | C58: Alice | D58: West | E58: 267.78 | F58: 32 | G58: Electronics | H58: 2678.99 | I58: 3152.2799999999997 | J58: Returning | K58: 0.22 | L58: Cash | M58: Retail | N58: West-Alice | O58: =IF(E58>AVERAGE($E$2:$E$1001),"High","Low") -> Low
A59: 1053 | B59: 45201 | C59: David | D59: East | E59: 7724.57 | F59: 29 | G59: Electronics | H59: 3741.3 | I59: 4061.04 | J59: Returning | K59: 0.21 | L59: Credit Card | M59: Online | N59: East-David | O59: =IF(E59>AVERAGE($E$2:$E$1001),"High","Low") -> High
A60: 1002 | B60: 45138 | C60: David | D60: East | E60: 8090.84 | F60: 21 | G60: Clothing | H60: 4138.41 | I60: 4361.7 | J60: Returning | K60: 0.07 | L60: Credit Card | M60: Retail | N60: East-David | O60: =IF(E60>AVERAGE($E$2:$E$1001),"High","Low") -> High
A61: 1084 | B61: 45151 | C61: Alice | D61: West | E61: 1290.05 | F61: 21 | G61: Furniture | H61: 3497.98 | I61: 3765.31 | J61: New | K61: 0.08 | L61: Cash | M61: Online | N61: West-Alice | O61: =IF(E61>AVERAGE($E$2:$E$1001),"High","Low") -> Low
A62: 1092 | B62: 44946 | C62: Charlie | D62: East | E62: 2729.27 | F62: 40 | G62: Electronics | H62: 4624.16 | I62: 4731.98 | J62: New | K62: 0.2 | L62: Bank Transfer | M62: Retail | N62: East-Charlie | O62: =IF(E62>AVERAGE($E$2:$E$1001),"High","Low") -> Low
A63: 1060 | B63: 45039 | C63: Eve | D63: East | E63: 273.77 | F63: 23 | G63: Clothing | H63: 4110.6 | I63: 4488.370000000001 | J63: New | K63: 0.12 | L63: Credit Card | M63: Online | N63: East-Eve | O63: =IF(E63>AVERAGE($E$2:$E$1001),"High","Low") -> Low
A64: 1071 | B64: 45066 | C64: Eve | D64: West | E64: 3003.76 | F64: 6 | G64: Furniture | H64: 2831.23 | I64: 3206.98 | J64: Returning | K64: 0.06 | L64: Bank Transfer | M64: Retail | N64: West-Eve | O64: =IF(E64>AVERAGE($E$2:$E$1001),"High","Low") -> Low
A65: 1044 | B65: 44973 | C65: David | D65: South | E65: 7754.1 | F65: 22 | G65: Food | H65: 3373.46 | I65: 3454.76 | J65: Returning | K65: 0.22 | L65: Bank Transfer | M65: Retail | N65: South-David | O65: =IF(E65>AVERAGE($E$2:$E$1001),"High","Low") -> High
A66: 1008 | B66: 44927 | C66: Eve | D66: North | E66: 5227.81 | F66: 38 | G66: Clothing | H66: 4635.23 | I66: 5075.44 | J66: Returning | K66: 0.05 | L66: Cash | M66: Online | N66: North-Eve | O66: =IF(E66>AVERAGE($E$2:$E$1001),"High","Low") -> High
A67: 1047 | B67: 45016 | C67: Alice | D67: East | E67: 3546.15 | F67: 37 | G67: Electronics | H67: 3114.88 | I67: 3256.78 | J67: Returning | K67: 0.26 | L67: Credit Card | M67: Online | N67: East-Alice | O67: =IF(E67>AVERAGE($E$2:$E$1001),"High","Low") -> Low
A68: 1035 | B68: 45068 | C68: Alice | D68: South | E68: 3780.22 | F68: 45 | G68: Food | H68: 4132.79 | I68: 4624.1 | J68: New | K68: 0.15 | L68: Credit Card | M68: Retail | N68: South-Alice | O68: =IF(E68>AVERAGE($E$2:$E$1001),"High","Low") -> Low
A69: 1078 | B69: 45246 | C69: David | D69: East | E69: 113.4 | F69: 8 | G69: Furniture | H69: 3459.61 | I69: 3657.23 | J69: Returning | K69: 0.03 | L69: Bank Transfer | M69: Online | N69: East-David | O69: =IF(E69>AVERAGE($E$2:$E$1001),"High","Low") -> Low
A70: 1081 | B70: 44964 | C70: David | D70: East | E70: 3068.03 | F70: 41 | G70: Furniture | H70: 2782.08 | I70: 2879.24 | J70: New | K70: 0.21 | L70: Bank Transfer | M70: Online | N70: East-David | O70: =IF(E70>AVERAGE($E$2:$E$1001),"High","Low") -> Low
A71: 1036 | B71: 45219 | C71: David | D71: North | E71: 6499.94 | F71: 49 | G71: Clothing | H71: 1247.1 | I71: 1429.4399999999998 | J71: New | K71: 0.16 | L71: Cash | M71: Online | N71: North-David | O71: =IF(E71>AVERAGE($E$2:$E$1001),"High","Low") -> High
A72: 1050 | B72: 45065 | C72: Charlie | D72: East | E72: 9744.52 | F72: 35 | G72: Clothing | H72: 2158.69 | I72: 2384.38 | J72: Returning | K72: 0.09 | L72: Bank Transfer | M72: Retail | N72: East-Charlie | O72: =IF(E72>AVERAGE($E$2:$E$1001),"High","Low") -> High
A73: 1004 | B73: 45282 | C73: Eve | D73: North | E73: 8485.9 | F73: 11 | G73: Clothing | H73: 4840.33 | I73: 4884.29 | J73: New | K73: 0.13 | L73: Cash | M73: Online | N73: North-Eve | O73: =IF(E73>AVERAGE($E$2:$E$1001),"High","Low") -> High
A74: 1002 | B74: 45259 | C74: David | D74: North | E74: 333.59 | F74: 24 | G74: Furniture | H74: 3305.94 | I74: 3599.27 | J74: New | K74: 0.09 | L74: Credit Card | M74: Retail | N74: North-David | O74: =IF(E74>AVERAGE($E$2:$E$1001),"High","Low") -> Low
A75: 1006 | B75: 45185 | C75: Bob | D75: North | E75: 8995.75 | F75: 49 | G75: Food | H75: 2843.76 | I75: 3146.6000000000004 | J75: New | K75: 0.08 | L75: Cash | M75: Retail | N75: North-Bob | O75: =IF(E75>AVERAGE($E$2:$E$1001),"High","Low") -> High
A76: 1054 | B76: 45087 | C76: Bob | D76: South | E76: 7853.66 | F76: 21 | G76: Furniture | H76: 4668.14 | I76: 5040.22 | J76: New | K76: 0.05 | L76: Bank Transfer | M76: Online | N76: South-Bob | O76: =IF(E76>AVERAGE($E$2:$E$1001),"High","Low") -> High
A77: 1004 | B77: 45104 | C77: Alice | D77: West | E77: 7825.72 | F77: 2 | G77: Electronics | H77: 2953.23 | I77: 2977.52 | J77: Returning | K77: 0.11 | L77: Credit Card | M77: Retail | N77: West-Alice | O77: =IF(E77>AVERAGE($E$2:$E$1001),"High","Low") -> High
A78: 1054 | B78: 44936 | C78: Eve | D78: South | E78: 4634.16 | F78: 40 | G78: Furniture | H78: 2654.11 | I78: 2929.32 | J78: Returning | K78: 0.08 | L78: Cash | M78: Online | N78: South-Eve | O78: =IF(E78>AVERAGE($E$2:$E$1001),"High","Low") -> Low
A79: 1093 | B79: 45187 | C79: David | D79: West | E79: 4040.25 | F79: 19 | G79: Electronics | H79: 3808.59 | I79: 3844.51 | J79: New | K79: 0.21 | L79: Credit Card | M79: Online | N79: West-David | O79: =IF(E79>AVERAGE($E$2:$E$1001),"High","Low") -> Low
A80: 1063 | B80: 45064 | C80: Bob | D80: West | E80: 3098.87 | F80: 39 | G80: Food | H80: 3577.69 | I80: 3931.25 | J80: Returning | K80: 0.21 | L80: Cash | M80: Retail | N80: West-Bob | O80: =IF(E80>AVERAGE($E$2:$E$1001),"High","Low") -> Low
A81: 1018 | B81: 45098 | C81: Eve | D81: North | E81: 750.38 | F81: 28 | G81: Clothing | H81: 1006.14 | I81: 1043.45 | J81: New | K81: 0.15 | L81: Bank Transfer | M81: Retail | N81: North-Eve | O81: =IF(E81>AVERAGE($E$2:$E$1001),"High","Low") -> Low
A82: 1090 | B82: 44939 | C82: Alice | D82: East | E82: 2359.53 | F82: 17 | G82: Clothing | H82: 2382.98 | I82: 2839.73 | J82: Returning | K82: 0.23 | L82: Bank Transfer | M82: Retail | N82: East-Alice | O82: =IF(E82>AVERAGE($E$2:$E$1001),"High","Low") -> Low
A83: 1044 | B83: 45094 | C83: Charlie | D83: North | E83: 2541.38 | F83: 6 | G83: Furniture | H83: 2388.95 | I83: 2742.97 | J83: Returning | K83: 0.25 | L83: Credit Card | M83: Retail | N83: North-Charlie | O83: =IF(E83>AVERAGE($E$2:$E$1001),"High","Low") -> Low
A84: 1034 | B84: 45056 | C84: Eve | D84: East | E84: 4892.36 | F84: 19 | G84: Clothing | H84: 1922.21 | I84: 2180.83 | J84: Returning | K84: 0.17 | L84: Credit Card | M84: Retail | N84: East-Eve | O84: =IF(E84>AVERAGE($E$2:$E$1001),"High","Low") -> Low
A85: 1074 | B85: 45010 | C85: Eve | D85: West | E85: 7499.7 | F85: 38 | G85: Food | H85: 2610.6 | I85: 2836.94 | J85: Returning | K85: 0.19 | L85: Credit Card | M85: Online | N85: West-Eve | O85: =IF(E85>AVERAGE($E$2:$E$1001),"High","Low") -> High
A86: 1062 | B86: 45247 | C86: Charlie | D86: North | E86: 4790.72 | F86: 28 | G86: Clothing | H86: 2094.88 | I86: 2168.9100000000003 | J86: Returning | K86: 0.08 | L86: Cash | M86: Retail | N86: North-Charlie | O86: =IF(E86>AVERAGE($E$2:$E$1001),"High","Low") -> Low
A87: 1100 | B87: 45245 | C87: Eve | D87: East | E87: 672.66 | F87: 2 | G87: Furniture | H87: 1036.76 | I87: 1189.35 | J87: New | K87: 0.27 | L87: Bank Transfer | M87: Online | N87: East-Eve | O87: =IF(E87>AVERAGE($E$2:$E$1001),"High","Low") -> Low
A88: 1014 | B88: 45027 | C88: Alice | D88: South | E88: 9582.12 | F88: 38 | G88: Food | H88: 2091.21 | I88: 2527 | J88: Returning | K88: 0.01 | L88: Credit Card | M88: Online | N88: South-Alice | O88: =IF(E88>AVERAGE($E$2:$E$1001),"High","Low") -> High
A89: 1095 | B89: 45255 | C89: Alice | D89: East | E89: 9432.97 | F89: 37 | G89: Electronics | H89: 407.77 | I89: 860.95 | J89: New | K89: 0.1 | L89: Credit Card | M89: Retail | N89: East-Alice | O89: =IF(E89>AVERAGE($E$2:$E$1001),"High","Low") -> High
A90: 1048 | B90: 45199 | C90: Charlie | D90: North | E90: 7873.38 | F90: 4 | G90: Furniture | H90: 2900.14 | I90: 2910.5099999999998 | J90: New | K90: 0.22 | L90: Credit Card | M90: Retail | N90: North-Charlie | O90: =IF(E90>AVERAGE($E$2:$E$1001),"High","Low") -> High
A91: 1015 | B91: 45191 | C91: David | D91: South | E91: 9914.15 | F91: 22 | G91: Electronics | H91: 4275.59 | I91: 4576.72 | J91: Returning | K91: 0.02 | L91: Cash | M91: Retail | N91: South-David | O91: =IF(E91>AVERAGE($E$2:$E$1001),"High","Low") -> High
A92: 1072 | B92: 44964 | C92: Bob | D92: East | E92: 5490.38 | F92: 26 | G92: Food | H92: 3640.17 | I92: 4002.63 | J92: New | K92: 0.05 | L92: Credit Card | M92: Retail | N92: East-Bob | O92: =IF(E92>AVERAGE($E$2:$E$1001),"High","Low") -> High
A93: 1078 | B93: 45020 | C93: David | D93: East | E93: 9631.41 | F93: 49 | G93: Furniture | H93: 1833.95 | I93: 2147.14 | J93: Returning | K93: 0.18 | L93: Credit Card | M93: Retail | N93: East-David | O93: =IF(E93>AVERAGE($E$2:$E$1001),"High","Low") -> High
A94: 1087 | B94: 45021 | C94: Eve | D94: East | E94: 848.49 | F94: 43 | G94: Furniture | H94: 481 | I94: 531.02 | J94: New | K94: 0.17 | L94: Cash | M94: Online | N94: East-Eve | O94: =IF(E94>AVERAGE($E$2:$E$1001),"High","Low") -> Low
A95: 1062 | B95: 45231 | C95: Bob | D95: East | E95: 3720.24 | F95: 36 | G95: Food | H95: 1050.64 | I95: 1167.3300000000002 | J95: New | K95: 0.22 | L95: Cash | M95: Online | N95: East-Bob | O95: =IF(E95>AVERAGE($E$2:$E$1001),"High","Low") -> Low
A96: 1040 | B96: 44995 | C96: Charlie | D96: East | E96: 2331.27 | F96: 13 | G96: Clothing | H96: 2750.18 | I96: 2882.85 | J96: Returning | K96: 0.24 | L96: Credit Card | M96: Online | N96: East-Charlie | O96: =IF(E96>AVERAGE($E$2:$E$1001),"High","Low") -> Low
A97: 1085 | B97: 45244 | C97: Charlie | D97: South | E97: 2038.75 | F97: 32 | G97: Furniture | H97: 1074.93 | I97: 1492.48 | J97: Returning | K97: 0.04 | L97: Credit Card | M97: Retail | N97: South-Charlie | O97: =IF(E97>AVERAGE($E$2:$E$1001),"High","Low") -> Low
A98: 1080 | B98: 45162 | C98: Bob | D98: West | E98: 1493.95 | F98: 17 | G98: Furniture | H98: 2742.67 | I98: 2979.64 | J98: Returning | K98: 0.01 | L98: Cash | M98: Retail | N98: West-Bob | O98: =IF(E98>AVERAGE($E$2:$E$1001),"High","Low") -> Low
A99: 1082 | B99: 45260 | C99: Alice | D99: South | E99: 6261.9 | F99: 41 | G99: Electronics | H99: 1196.42 | I99: 1444.97 | J99: Returning | K99: 0.21 | L99: Bank Transfer | M99: Online | N99: South-Alice | O99: =IF(E99>AVERAGE($E$2:$E$1001),"High","Low") -> High
A100: 1053 | B100: 45063 | C100: Bob | D100: South | E100: 7835.09 | F100: 36 | G100: Clothing | H100: 4252.17 | I100: 4720.27 | J100: New | K100: 0.09 | L100: Cash | M100: Retail | N100: South-Bob | O100: =IF(E100>AVERAGE($E$2:$E$1001),"High","Low") -> High
...

Sheet Summary
A1: Summary
A3: Total Revenue | B3: =SUM(sales_data!E2:'sales_data'!E1001) -> 5019265.2
A4: Average Order Value | B4: =AVERAGE(sales_data!E2:'sales_data'!E1001) -> 5019.2652
A5: Number of Transactions | B5: =COUNT(sales_data!E2:'sales_data'!E1001) -> 1000
A6: Highest Sale | B6: =MAX(sales_data!E2:'sales_data'!E1001) -> 9989.04
A7: Lowest Sale | B7: =MIN(sales_data!E2:'sales_data'!E1001) -> 100.12
